ramsmod/__init__.py
ramsmod/fitting.py
ramsmod/generate_data.py
ramsmod/plotting.py
ramsmod/stats.py
ramsmod/utils.py
ramsmod/datasets/__init__.py
ramsmod/datasets/exponential_data.csv
ramsmod/datasets/interval-censored-2.csv
ramsmod/datasets/interval-censored.csv
ramsmod/datasets/lognormal_data.csv
ramsmod/datasets/right-censored-2.csv
ramsmod/datasets/right-censored.csv
ramsmod/datasets/weibull_data.csv
ramsmod-0.6.2.dist-info/LICENSE.rst
ramsmod-0.6.2.dist-info/METADATA
ramsmod-0.6.2.dist-info/WHEEL
ramsmod-0.6.2.dist-info/top_level.txt
ramsmod-0.6.2.dist-info/RECORD
