Metadata-Version: 2.1
Name: ramsmod
Version: 0.6.2
Summary: Python 3 library for reliability data analysis
Home-page: https://github.com/user/sean-reed
Author: Sean Reed
Author-email: sean@sean-reed.com
License: MIT
Download-URL: https://github.com/sean-reed/ramsmod/archive/v0.6.2.tar.gz
Platform: UNKNOWN
Classifier: Development Status :: 4 - Beta
Classifier: License :: OSI Approved :: MIT License
Classifier: Programming Language :: Python
Classifier: Programming Language :: Python :: 3.6
Classifier: Programming Language :: Python :: 3.7
Classifier: Programming Language :: Python :: 3.8
Classifier: Programming Language :: Python :: 3.9
Classifier: Topic :: Scientific/Engineering
Requires-Dist: pandas (>=0.23.0)
Requires-Dist: matplotlib (>=3.0)
Requires-Dist: numpy (>=1.14.0)
Requires-Dist: scipy (>=1.2.0)
